danssfmlpy/__init__.py
danssfmlpy/controls.py
danssfmlpy/libDansSfmlWrapper.so
danssfmlpy/media.py
danssfmlpy-1.9.0.dist-info/METADATA
danssfmlpy-1.9.0.dist-info/WHEEL
danssfmlpy-1.9.0.dist-info/top_level.txt
danssfmlpy-1.9.0.dist-info/RECORD
