Metadata-Version: 2.1
Name: danssfmlpy
Version: 1.9.0
Summary: SFML wrapper for Python
Home-page: http://github.com/dansgithubuser/danssfml
Author: danspypiuser
Author-email: dansonlinepresence@gmail.com
License: MIT
Platform: UNKNOWN
Requires-Dist: obvious
